Topsis_Kunalkhullar_101903418/101903418.py
Topsis_KunalKhullar_101903418-0.3.dist-info/METADATA
Topsis_KunalKhullar_101903418-0.3.dist-info/WHEEL
Topsis_KunalKhullar_101903418-0.3.dist-info/top_level.txt
Topsis_KunalKhullar_101903418-0.3.dist-info/RECORD
