Metadata-Version: 2.1
Name: Topsis-KunalKhullar-101903418
Version: 0.3
Summary: Implementation of TOPSIS
Home-page: UNKNOWN
Author: Kunal Khullar
Author-email: kkhullar_be19@thapar.edu
License: MIT
Keywords: TOPSIS
Platform: UNKNOWN
Classifier: Development Status :: 3 - Alpha
Classifier: Intended Audience :: Developers
Classifier: Topic :: Software Development :: Build Tools
Classifier: License :: OSI Approved :: MIT License
Classifier: Operating System :: Microsoft :: Windows :: Windows 10
Classifier: Programming Language :: Python :: 3.6
Classifier: Programming Language :: Python :: 2
Classifier: Programming Language :: Python :: 2.7
Classifier: Programming Language :: Python :: 3
Classifier: Programming Language :: Python :: 3.4
Classifier: Programming Language :: Python :: 3.5
Requires-Dist: pandas
Requires-Dist: numpy
